[
    {
        "question": "How much dividend did NSIC pay for FY24?",
        "options": [
            "₹37.97 crore",
            "₹35 crore",
            "₹40 crore",
            "₹38 crore"
        ],
        "answer": "₹37.97 crore"
    },
    {
        "question": "What is the number of credit cards issued by SBI Card?",
        "options": [
            "Over 20 million",
            "Over 15 million",
            "Over 25 million",
            "Over 18 million"
        ],
        "answer": "Over 20 million"
    },
    {
        "question": "Who won the Aster Guardians Global Nursing Award 2024?",
        "options": [
            "Maria Victoria Juan",
            "Anna Qabale Duba",
            "Julia Downing",
            "Lilian Pakhomova"
        ],
        "answer": "Maria Victoria Juan"
    },
    {
        "question": "What is the date of International Day for the Abolition of Slavery?",
        "options": [
            "December 2",
            "December 1",
            "December 3",
            "December 4"
        ],
        "answer": "December 2"
    },
    {
        "question": "When is World AIDS Day observed?",
        "options": [
            "December 1",
            "December 2",
            "November 30",
            "December 3"
        ],
        "answer": "December 1"
    },
    {
        "question": "What is the date of International Day of Persons with Disabilities?",
        "options": [
            "December 3",
            "December 2",
            "December 4",
            "December 5"
        ],
        "answer": "December 3"
    },
    {
        "question": "When is Indian Navy Day celebrated?",
        "options": [
            "December 4",
            "December 3",
            "December 5",
            "December 6"
        ],
        "answer": "December 4"
    },
    {
        "question": "What is the date of World Soil Day?",
        "options": [
            "December 5",
            "December 4",
            "December 6",
            "December 7"
        ],
        "answer": "December 5"
    },
    {
        "question": "When is International Volunteer Day?",
        "options": [
            "December 5",
            "December 4",
            "December 6",
            "December 7"
        ],
        "answer": "December 5"
    },
    {
        "question": "What is the date of Mahaparinirvan Diwas?",
        "options": [
            "December 6",
            "December 5",
            "December 7",
            "December 8"
        ],
        "answer": "December 6"
    },
    {
        "question": "When is Armed Forces Flag Day observed?",
        "options": [
            "December 7",
            "December 6",
            "December 8",
            "December 9"
        ],
        "answer": "December 7"
    },
    {
        "question": "What global chess rating did Arjun Erigaisi join?",
        "options": [
            "2800 ELO",
            "2750 ELO",
            "2850 ELO",
            "2700 ELO"
        ],
        "answer": "2800 ELO"
    },
    {
        "question": "Who won the Junior Hockey Asia Cup?",
        "options": [
            "India (defeating Pakistan 5-3)",
            "Pakistan (defeating India 5-3)",
            "India (defeating South Korea 5-3)",
            "South Korea (defeating India 5-3)"
        ],
        "answer": "India (defeating Pakistan 5-3)"
    },
    {
        "question": "What is the name of the event celebrating youth innovation in Battery Technology?",
        "options": [
            "SheSTEM 2024",
            "TechYouth 2024",
            "InnovateHer 2024",
            "FutureTech 2024"
        ],
        "answer": "SheSTEM 2024"
    },
    {
        "question": "Which actor announced retirement from acting?",
        "options": [
            "Vikrant Massey",
            "Shah Rukh Khan",
            "Aamir Khan",
            "Akshay Kumar"
        ],
        "answer": "Vikrant Massey"
    },
    {
        "question": "What disease did India declare as notifiable to reduce mortality?",
        "options": [
            "Snakebite",
            "Rabies",
            "Tuberculosis",
            "Malaria"
        ],
        "answer": "Snakebite"
    },
    {
        "question": "Which global drug policy-making body will India chair?",
        "options": [
            "68th UN Commission on Narcotic Drugs (CND)",
            "World Health Organization (WHO)",
            "International Narcotics Control Board (INCB)",
            "United Nations Office on Drugs and Crime (UNODC)"
        ],
        "answer": "68th UN Commission on Narcotic Drugs (CND)"
    },
    {
        "question": "What is the aim for snakebite deaths reduction by 2030?",
        "options": [
            "Halving the mortality rate",
            "Reducing by 30%",
            "Eliminating completely",
            "Reducing by 75%"
        ],
        "answer": "Halving the mortality rate"
    },
    {
        "question": "What is the new portal launched for legal metrology?",
        "options": [
            "eMaap Portal",
            "eMetrology Portal",
            "LegalMetrologyOnline",
            "MeasureRight Portal"
        ],
        "answer": "eMaap Portal"
    },
    {
        "question": "Which state announced a new farmer subsidy scheme?",
        "options": [
            "Telangana (Rythu Bharosa)",
            "Andhra Pradesh (YSR Rythu Bharosa)",
            "Karnataka (PM-KISAN)",
            "Maharashtra (Krishi Sanman Nidhi)"
        ],
        "answer": "Telangana (Rythu Bharosa)"
    },
    {
        "question": "What is the date of International Civil Aviation Day?",
        "options": [
            "December 7",
            "December 6",
            "December 8",
            "December 9"
        ],
        "answer": "December 7"
    },
    {
        "question": "When is World Meditation Day declared by UNGA?",
        "options": [
            "December 21",
            "December 1",
            "December 11",
            "December 20"
        ],
        "answer": "December 21"
    },
    {
        "question": "Who became Sri Lanka's second female Chief Justice?",
        "options": [
            "Murdu Fernando",
            "Shirani Bandaranayake",
            "K. Sripavan",
            "Mohan Peiris"
        ],
        "answer": "Murdu Fernando"
    },
    {
        "question": "What is the name of the drone delivered by Adani to the Indian Navy?",
        "options": [
            "Drishti-10",
            "Garuda-10",
            "Netra-10",
            "Surya-10"
        ],
        "answer": "Drishti-10"
    },
    {
        "question": "Which sports tournament did PV Sindhu win in 2024?",
        "options": [
            "Syed Modi 2024",
            "All England Open 2024",
            "BWF World Championships 2024",
            "India Open 2024"
        ],
        "answer": "Syed Modi 2024"
    },
    {
        "question": "What is the government initiative to modernize the Public Distribution System?",
        "options": [
            "Anna 'Chakra'",
            "Digital PDS",
            "Modern PDS",
            "Food Security Mission"
        ],
        "answer": "Anna 'Chakra'"
    },
    {
        "question": "What percentage improvement did girls' secondary education see?",
        "options": [
            "79.4% Gross Enrollment Ratio",
            "75%",
            "80%",
            "82%"
        ],
        "answer": "79.4% Gross Enrollment Ratio"
    },
    {
        "question": "Which military drill between India and Malaysia focuses on jungle terrain?",
        "options": [
            "Harimau Shakti 2024",
            "Exercise Shakti",
            "Garuda Shakti",
            "Samudra Shakti"
        ],
        "answer": "Harimau Shakti 2024"
    },
    {
        "question": "What is the name of the cybersecurity hub Google will establish in Hyderabad?",
        "options": [
            "Safety Engineering Centre",
            "Advanced Security Hub",
            "Cybersecurity Excellence Center",
            "Google Security Center"
        ],
        "answer": "Safety Engineering Centre"
    },
    {
        "question": "What is the new digital literacy milestone in rural India?",
        "options": [
            "6.39 crore individuals trained",
            "5 crore",
            "7 crore",
            "6.5 crore"
        ],
        "answer": "6.39 crore individuals trained"
    },
    {
        "question": "Which article did the Supreme Court invoke to grant permanent commission to a woman Army officer?",
        "options": [
            "Article 142",
            "Article 370",
            "Article 32",
            "Article 21"
        ],
        "answer": "Article 142"
    },
    {
        "question": "Which bill aims to simplify the legal framework for Indian Railways?",
        "options": [
            "Railways (Amendment) Bill 2024",
            "Indian Railways Act 2024",
            "Railway Modernization Bill 2024",
            "Railway Safety Bill 2024"
        ],
        "answer": "Railways (Amendment) Bill 2024"
    },
    {
        "question": "By what year does India plan to triple its atomic power capacity?",
        "options": [
            "2031",
            "2030",
            "2032",
            "2035"
        ],
        "answer": "2031"
    },
    {
        "question": "Which technology was trialed to improve water quality in Delhi Zoo?",
        "options": [
            "Nano Bubble Technology",
            "Reverse Osmosis",
            "UV Filtration",
            "Ozone Treatment"
        ],
        "answer": "Nano Bubble Technology"
    },
    {
        "question": "What is the amount of annual farmer subsidy announced in Telangana?",
        "options": [
            "₹15,000",
            "₹12,000",
            "₹16,000",
            "₹14,000"
        ],
        "answer": "₹15,000"
    },
    {
        "question": "Which foundation received FCRA licenses for foreign funding?",
        "options": [
            "CNI and USIN Foundation",
            "CRY and Goonj",
            "Oxfam India and Care India",
            "Save the Children India and Pratham"
        ],
        "answer": "CNI and USIN Foundation"
    }
]